Workbook

Sheet Menú y Pantallas
A1: Módulo N° | B1: Módulo | C1: Código | D1: Pantalla | E1: Descripción | F1: Roles
A2: 1 | B2: Dashboard e Indicadores | C2: 1.1 | D2: Visión general | E2: Pedidos por estado, ocupación y cumplimiento por bodega o consolidado | F2: ADM, JB, GER
A3: 1 | B3: Dashboard e Indicadores | C3: 1.2 | D3: KPIs operativos | E3: Exactitud de inventario, dock-to-stock, líneas por hora, mermas, OTIF | F3: ADM, JB, AUD, GER
A4: 1 | B4: Dashboard e Indicadores | C4: 1.3 | D4: Alertas y excepciones | E4: Quiebres, vencimientos, inconsistencias y pedidos atrasados con responsable | F4: ADM, JB, COM, TRA
A5: 2 | B5: Multi-Bodega y Ubicaciones | C5: 2.1 | D5: Consolidado Cuenta Padre | E5: Stock global por SKU, estado y bodega, con comparativos | F5: ADM, JB, COM, GER
A6: 2 | B6: Multi-Bodega y Ubicaciones | C6: 2.2 | D6: Bodegas | E6: Alta y edición de bodegas hijas, horarios y zona horaria | F6: ADM
A7: 2 | B7: Multi-Bodega y Ubicaciones | C7: 2.3 | D7: Ubicaciones y zonas | E7: Pasillo-Rack-Nivel-Bin, capacidad, tipo y estado | F7: ADM, JB
A8: 2 | B8: Multi-Bodega y Ubicaciones | C8: 2.4 | D8: Reglas de putaway y reposición | E8: Sugerencia de ubicación y mínimos/máximos de picking | F8: ADM, JB
A9: 2 | B9: Multi-Bodega y Ubicaciones | C9: 2.5 | D9: Traspasos inter-bodegas | E9: Solicitud, aprobación, tránsito y recepción de traslados | F9: JB, REC, PCK
A10: 3 | B10: Recepción e Ingresos | C10: 3.1 | D10: Agenda de muelles y ASN | E10: Citas de llegada y avisos anticipados del proveedor | F10: JB, REC
A11: 3 | B11: Recepción e Ingresos | C11: 3.2 | D11: Recepción contra OC | E11: Conteo, escaneo y registro contra orden de compra | F11: REC, JB
A12: 3 | B12: Recepción e Ingresos | C12: 3.3 | D12: Inspección de calidad | E12: Checklist, fotos y resultado aprobado/rechazado | F12: CAL, JB
A13: 3 | B13: Recepción e Ingresos | C13: 3.4 | D13: Putaway | E13: Tareas de ubicación en terminal móvil | F13: REC
... A68: 11 | B68: Configuración General | C68: 11.10 | D68: Documentos fiscales | E68: Formatos legales según país | F68: ADM, GER
A70: Total pantallas | D70: =COUNTA(D2:D68) -> 67
A71: Leyenda de roles en la hoja 'Roles'. Código = Módulo.Pantalla. Pantallas de picking, putaway y conteo ciego (3.4, 7.3, 10.5) se diseñan para móvil.

Sheet Matriz Roles
A1: Código | B1: Pantalla | C1: ADM | D1: JB | E1: REC | F1: PCK | G1: PKG | H1: CAL | I1: AUD | J1: COM | K1: TRA | L1: GER
A2: ='Menú y Pantallas'!C2 -> 1.1 | B2: ='Menú y Pantallas'!D2 -> Visión general | C2: =IF(OR(ISNUMBER(SEARCH(C$1,'Menú y Pantallas'!$F2)),ISNUMBER(SEARCH("Todos",'Menú y Pantallas'!$F2))),"X","") -> X | D2: =IF(OR(ISNUMBER(SEARCH(D$1,'Menú y Pantallas'!$F2)),ISNUMBER(SEARCH("Todos",'Menú y Pantallas'!$F2))),"X","") -> X | E2: =IF(OR(ISNUMBER(SEARCH(E$1,'Menú y Pantallas'!$F2)),ISNUMBER(SEARCH("Todos",'Menú y Pantallas'!$F2))),"X","") | F2: =IF(OR(ISNUMBER(SEARCH(F$1,'Menú y Pantallas'!$F2)),ISNUMBER(SEARCH("Todos",'Menú y Pantallas'!$F2))),"X","") | G2: =IF(OR(ISNUMBER(SEARCH(G$1,'Menú y Pantallas'!$F2)),ISNUMBER(SEARCH("Todos",'Menú y Pantallas'!$F2))),"X","") | H2: =IF(OR(ISNUMBER(SEARCH(H$1,'Menú y Pantallas'!$F2)),ISNUMBER(SEARCH("Todos",'Menú y Pantallas'!$F2))),"X","") | I2: =IF(OR(ISNUMBER(SEARCH(I$1,'Menú y Pantallas'!$F2)),ISNUMBER(SEARCH("Todos",'Menú y Pantallas'!$F2))),"X","") | J2: =IF(OR(ISNUMBER(SEARCH(J$1,'Menú y Pantallas'!$F2)),ISNUMBER(SEARCH("Todos",'Menú y Pantallas'!$F2))),"X","") | ... L2: =IF(OR(ISNUMBER(SEARCH(L$1,'Menú y Pantallas'!$F2)),ISNUMBER(SEARCH("Todos",'Menú y Pantallas'!$F2))),"X","") -> X
A3: ='Menú y Pantallas'!C3 -> 1.2 | B3: ='Menú y Pantallas'!D3 -> KPIs operativos | C3: =IF(OR(ISNUMBER(SEARCH(C$1,'Menú y Pantallas'!$F3)),ISNUMBER(SEARCH("Todos",'Menú y Pantallas'!$F3))),"X","") -> X | D3: =IF(OR(ISNUMBER(SEARCH(D$1,'Menú y Pantallas'!$F3)),ISNUMBER(SEARCH("Todos",'Menú y Pantallas'!$F3))),"X","") -> X | E3: =IF(OR(ISNUMBER(SEARCH(E$1,'Menú y Pantallas'!$F3)),ISNUMBER(SEARCH("Todos",'Menú y Pantallas'!$F3))),"X","") | F3: =IF(OR(ISNUMBER(SEARCH(F$1,'Menú y Pantallas'!$F3)),ISNUMBER(SEARCH("Todos",'Menú y Pantallas'!$F3))),"X","") | G3: =IF(OR(ISNUMBER(SEARCH(G$1,'Menú y Pantallas'!$F3)),ISNUMBER(SEARCH("Todos",'Menú y Pantallas'!$F3))),"X","") | H3: =IF(OR(ISNUMBER(SEARCH(H$1,'Menú y Pantallas'!$F3)),ISNUMBER(SEARCH("Todos",'Menú y Pantallas'!$F3))),"X","") | I3: =IF(OR(ISNUMBER(SEARCH(I$1,'Menú y Pantallas'!$F3)),ISNUMBER(SEARCH("Todos",'Menú y Pantallas'!$F3))),"X","") -> X | J3: =IF(OR(ISNUMBER(SEARCH(J$1,'Menú y Pantallas'!$F3)),ISNUMBER(SEARCH("Todos",'Menú y Pantallas'!$F3))),"X","") | ... L3: =IF(OR(ISNUMBER(SEARCH(L$1,'Menú y Pantallas'!$F3)),ISNUMBER(SEARCH("Todos",'Menú y Pantallas'!$F3))),"X","") -> X
A4: ='Menú y Pantallas'!C4 -> 1.3 | B4: ='Menú y Pantallas'!D4 -> Alertas y excepciones | C4: =IF(OR(ISNUMBER(SEARCH(C$1,'Menú y Pantallas'!$F4)),ISNUMBER(SEARCH("Todos",'Menú y Pantallas'!$F4))),"X","") -> X | D4: =IF(OR(ISNUMBER(SEARCH(D$1,'Menú y Pantallas'!$F4)),ISNUMBER(SEARCH("Todos",'Menú y Pantallas'!$F4))),"X","") -> X | E4: =IF(OR(ISNUMBER(SEARCH(E$1,'Menú y Pantallas'!$F4)),ISNUMBER(SEARCH("Todos",'Menú y Pantallas'!$F4))),"X","") | F4: =IF(OR(ISNUMBER(SEARCH(F$1,'Menú y Pantallas'!$F4)),ISNUMBER(SEARCH("Todos",'Menú y Pantallas'!$F4))),"X","") | G4: =IF(OR(ISNUMBER(SEARCH(G$1,'Menú y Pantallas'!$F4)),ISNUMBER(SEARCH("Todos",'Menú y Pantallas'!$F4))),"X","") | H4: =IF(OR(ISNUMBER(SEARCH(H$1,'Menú y Pantallas'!$F4)),ISNUMBER(SEARCH("Todos",'Menú y Pantallas'!$F4))),"X","") | I4: =IF(OR(ISNUMBER(SEARCH(I$1,'Menú y Pantallas'!$F4)),ISNUMBER(SEARCH("Todos",'Menú y Pantallas'!$F4))),"X","") | J4: =IF(OR(ISNUMBER(SEARCH(J$1,'Menú y Pantallas'!$F4)),ISNUMBER(SEARCH("Todos",'Menú y Pantallas'!$F4))),"X","") -> X | ... L4: =IF(OR(ISNUMBER(SEARCH(L$1,'Menú y Pantallas'!$F4)),ISNUMBER(SEARCH("Todos",'Menú y Pantallas'!$F4))),"X","")
A5: ='Menú y Pantallas'!C5 -> 2.1 | B5: ='Menú y Pantallas'!D5 -> Consolidado Cuenta Padre | C5: =IF(OR(ISNUMBER(SEARCH(C$1,'Menú y Pantallas'!$F5)),ISNUMBER(SEARCH("Todos",'Menú y Pantallas'!$F5))),"X","") -> X | D5: =IF(OR(ISNUMBER(SEARCH(D$1,'Menú y Pantallas'!$F5)),ISNUMBER(SEARCH("Todos",'Menú y Pantallas'!$F5))),"X","") -> X | E5: =IF(OR(ISNUMBER(SEARCH(E$1,'Menú y Pantallas'!$F5)),ISNUMBER(SEARCH("Todos",'Menú y Pantallas'!$F5))),"X","") | F5: =IF(OR(ISNUMBER(SEARCH(F$1,'Menú y Pantallas'!$F5)),ISNUMBER(SEARCH("Todos",'Menú y Pantallas'!$F5))),"X","") | G5: =IF(OR(ISNUMBER(SEARCH(G$1,'Menú y Pantallas'!$F5)),ISNUMBER(SEARCH("Todos",'Menú y Pantallas'!$F5))),"X","") | H5: =IF(OR(ISNUMBER(SEARCH(H$1,'Menú y Pantallas'!$F5)),ISNUMBER(SEARCH("Todos",'Menú y Pantallas'!$F5))),"X","") | I5: =IF(OR(ISNUMBER(SEARCH(I$1,'Menú y Pantallas'!$F5)),ISNUMBER(SEARCH("Todos",'Menú y Pantallas'!$F5))),"X","") | J5: =IF(OR(ISNUMBER(SEARCH(J$1,'Menú y Pantallas'!$F5)),ISNUMBER(SEARCH("Todos",'Menú y Pantallas'!$F5))),"X","") -> X | ... L5: =IF(OR(ISNUMBER(SEARCH(L$1,'Menú y Pantallas'!$F5)),ISNUMBER(SEARCH("Todos",'Menú y Pantallas'!$F5))),"X","") -> X
A6: ='Menú y Pantallas'!C6 -> 2.2 | B6: ='Menú y Pantallas'!D6 -> Bodegas | C6: =IF(OR(ISNUMBER(SEARCH(C$1,'Menú y Pantallas'!$F6)),ISNUMBER(SEARCH("Todos",'Menú y Pantallas'!$F6))),"X","") -> X | D6: =IF(OR(ISNUMBER(SEARCH(D$1,'Menú y Pantallas'!$F6)),ISNUMBER(SEARCH("Todos",'Menú y Pantallas'!$F6))),"X","") | E6: =IF(OR(ISNUMBER(SEARCH(E$1,'Menú y Pantallas'!$F6)),ISNUMBER(SEARCH("Todos",'Menú y Pantallas'!$F6))),"X","") | F6: =IF(OR(ISNUMBER(SEARCH(F$1,'Menú y Pantallas'!$F6)),ISNUMBER(SEARCH("Todos",'Menú y Pantallas'!$F6))),"X","") | G6: =IF(OR(ISNUMBER(SEARCH(G$1,'Menú y Pantallas'!$F6)),ISNUMBER(SEARCH("Todos",'Menú y Pantallas'!$F6))),"X","") | H6: =IF(OR(ISNUMBER(SEARCH(H$1,'Menú y Pantallas'!$F6)),ISNUMBER(SEARCH("Todos",'Menú y Pantallas'!$F6))),"X","") | I6: =IF(OR(ISNUMBER(SEARCH(I$1,'Menú y Pantallas'!$F6)),ISNUMBER(SEARCH("Todos",'Menú y Pantallas'!$F6))),"X","") | J6: =IF(OR(ISNUMBER(SEARCH(J$1,'Menú y Pantallas'!$F6)),ISNUMBER(SEARCH("Todos",'Menú y Pantallas'!$F6))),"X","") | ... L6: =IF(OR(ISNUMBER(SEARCH(L$1,'Menú y Pantallas'!$F6)),ISNUMBER(SEARCH("Todos",'Menú y Pantallas'!$F6))),"X","")
A7: ='Menú y Pantallas'!C7 -> 2.3 | B7: ='Menú y Pantallas'!D7 -> Ubicaciones y zonas | C7: =IF(OR(ISNUMBER(SEARCH(C$1,'Menú y Pantallas'!$F7)),ISNUMBER(SEARCH("Todos",'Menú y Pantallas'!$F7))),"X","") -> X | D7: =IF(OR(ISNUMBER(SEARCH(D$1,'Menú y Pantallas'!$F7)),ISNUMBER(SEARCH("Todos",'Menú y Pantallas'!$F7))),"X","") -> X | E7: =IF(OR(ISNUMBER(SEARCH(E$1,'Menú y Pantallas'!$F7)),ISNUMBER(SEARCH("Todos",'Menú y Pantallas'!$F7))),"X","") | F7: =IF(OR(ISNUMBER(SEARCH(F$1,'Menú y Pantallas'!$F7)),ISNUMBER(SEARCH("Todos",'Menú y Pantallas'!$F7))),"X","") | G7: =IF(OR(ISNUMBER(SEARCH(G$1,'Menú y Pantallas'!$F7)),ISNUMBER(SEARCH("Todos",'Menú y Pantallas'!$F7))),"X","") | H7: =IF(OR(ISNUMBER(SEARCH(H$1,'Menú y Pantallas'!$F7)),ISNUMBER(SEARCH("Todos",'Menú y Pantallas'!$F7))),"X","") | I7: =IF(OR(ISNUMBER(SEARCH(I$1,'Menú y Pantallas'!$F7)),ISNUMBER(SEARCH("Todos",'Menú y Pantallas'!$F7))),"X","") | J7: =IF(OR(ISNUMBER(SEARCH(J$1,'Menú y Pantallas'!$F7)),ISNUMBER(SEARCH("Todos",'Menú y Pantallas'!$F7))),"X","") | ... L7: =IF(OR(ISNUMBER(SEARCH(L$1,'Menú y Pantallas'!$F7)),ISNUMBER(SEARCH("Todos",'Menú y Pantallas'!$F7))),"X","")
A8: ='Menú y Pantallas'!C8 -> 2.4 | B8: ='Menú y Pantallas'!D8 -> Reglas de putaway y reposición | C8: =IF(OR(ISNUMBER(SEARCH(C$1,'Menú y Pantallas'!$F8)),ISNUMBER(SEARCH("Todos",'Menú y Pantallas'!$F8))),"X","") -> X | D8: =IF(OR(ISNUMBER(SEARCH(D$1,'Menú y Pantallas'!$F8)),ISNUMBER(SEARCH("Todos",'Menú y Pantallas'!$F8))),"X","") -> X | E8: =IF(OR(ISNUMBER(SEARCH(E$1,'Menú y Pantallas'!$F8)),ISNUMBER(SEARCH("Todos",'Menú y Pantallas'!$F8))),"X","") | F8: =IF(OR(ISNUMBER(SEARCH(F$1,'Menú y Pantallas'!$F8)),ISNUMBER(SEARCH("Todos",'Menú y Pantallas'!$F8))),"X","") | G8: =IF(OR(ISNUMBER(SEARCH(G$1,'Menú y Pantallas'!$F8)),ISNUMBER(SEARCH("Todos",'Menú y Pantallas'!$F8))),"X","") | H8: =IF(OR(ISNUMBER(SEARCH(H$1,'Menú y Pantallas'!$F8)),ISNUMBER(SEARCH("Todos",'Menú y Pantallas'!$F8))),"X","") | I8: =IF(OR(ISNUMBER(SEARCH(I$1,'Menú y Pantallas'!$F8)),ISNUMBER(SEARCH("Todos",'Menú y Pantallas'!$F8))),"X","") | J8: =IF(OR(ISNUMBER(SEARCH(J$1,'Menú y Pantallas'!$F8)),ISNUMBER(SEARCH("Todos",'Menú y Pantallas'!$F8))),"X","") | ... L8: =IF(OR(ISNUMBER(SEARCH(L$1,'Menú y Pantallas'!$F8)),ISNUMBER(SEARCH("Todos",'Menú y Pantallas'!$F8))),"X","")
A9: ='Menú y Pantallas'!C9 -> 2.5 | B9: ='Menú y Pantallas'!D9 -> Traspasos inter-bodegas | C9: =IF(OR(ISNUMBER(SEARCH(C$1,'Menú y Pantallas'!$F9)),ISNUMBER(SEARCH("Todos",'Menú y Pantallas'!$F9))),"X","") | D9: =IF(OR(ISNUMBER(SEARCH(D$1,'Menú y Pantallas'!$F9)),ISNUMBER(SEARCH("Todos",'Menú y Pantallas'!$F9))),"X","") -> X | E9: =IF(OR(ISNUMBER(SEARCH(E$1,'Menú y Pantallas'!$F9)),ISNUMBER(SEARCH("Todos",'Menú y Pantallas'!$F9))),"X","") -> X | F9: =IF(OR(ISNUMBER(SEARCH(F$1,'Menú y Pantallas'!$F9)),ISNUMBER(SEARCH("Todos",'Menú y Pantallas'!$F9))),"X","") -> X | G9: =IF(OR(ISNUMBER(SEARCH(G$1,'Menú y Pantallas'!$F9)),ISNUMBER(SEARCH("Todos",'Menú y Pantallas'!$F9))),"X","") | H9: =IF(OR(ISNUMBER(SEARCH(H$1,'Menú y Pantallas'!$F9)),ISNUMBER(SEARCH("Todos",'Menú y Pantallas'!$F9))),"X","") | I9: =IF(OR(ISNUMBER(SEARCH(I$1,'Menú y Pantallas'!$F9)),ISNUMBER(SEARCH("Todos",'Menú y Pantallas'!$F9))),"X","") | J9: =IF(OR(ISNUMBER(SEARCH(J$1,'Menú y Pantallas'!$F9)),ISNUMBER(SEARCH("Todos",'Menú y Pantallas'!$F9))),"X","") | ... L9: =IF(OR(ISNUMBER(SEARCH(L$1,'Menú y Pantallas'!$F9)),ISNUMBER(SEARCH("Todos",'Menú y Pantallas'!$F9))),"X","")
A10: ='Menú y Pantallas'!C10 -> 3.1 | B10: ='Menú y Pantallas'!D10 -> Agenda de muelles y ASN | C10: =IF(OR(ISNUMBER(SEARCH(C$1,'Menú y Pantallas'!$F10)),ISNUMBER(SEARCH("Todos",'Menú y Pantallas'!$F10))),"X","") | D10: =IF(OR(ISNUMBER(SEARCH(D$1,'Menú y Pantallas'!$F10)),ISNUMBER(SEARCH("Todos",'Menú y Pantallas'!$F10))),"X","") -> X | E10: =IF(OR(ISNUMBER(SEARCH(E$1,'Menú y Pantallas'!$F10)),ISNUMBER(SEARCH("Todos",'Menú y Pantallas'!$F10))),"X","") -> X | F10: =IF(OR(ISNUMBER(SEARCH(F$1,'Menú y Pantallas'!$F10)),ISNUMBER(SEARCH("Todos",'Menú y Pantallas'!$F10))),"X","") | G10: =IF(OR(ISNUMBER(SEARCH(G$1,'Menú y Pantallas'!$F10)),ISNUMBER(SEARCH("Todos",'Menú y Pantallas'!$F10))),"X","") | H10: =IF(OR(ISNUMBER(SEARCH(H$1,'Menú y Pantallas'!$F10)),ISNUMBER(SEARCH("Todos",'Menú y Pantallas'!$F10))),"X","") | I10: =IF(OR(ISNUMBER(SEARCH(I$1,'Menú y Pantallas'!$F10)),ISNUMBER(SEARCH("Todos",'Menú y Pantallas'!$F10))),"X","") | J10: =IF(OR(ISNUMBER(SEARCH(J$1,'Menú y Pantallas'!$F10)),ISNUMBER(SEARCH("Todos",'Menú y Pantallas'!$F10))),"X","") | ... L10: =IF(OR(ISNUMBER(SEARCH(L$1,'Menú y Pantallas'!$F10)),ISNUMBER(SEARCH("Todos",'Menú y Pantallas'!$F10))),"X","")
A11: ='Menú y Pantallas'!C11 -> 3.2 | B11: ='Menú y Pantallas'!D11 -> Recepción contra OC | C11: =IF(OR(ISNUMBER(SEARCH(C$1,'Menú y Pantallas'!$F11)),ISNUMBER(SEARCH("Todos",'Menú y Pantallas'!$F11))),"X","") | D11: =IF(OR(ISNUMBER(SEARCH(D$1,'Menú y Pantallas'!$F11)),ISNUMBER(SEARCH("Todos",'Menú y Pantallas'!$F11))),"X","") -> X | E11: =IF(OR(ISNUMBER(SEARCH(E$1,'Menú y Pantallas'!$F11)),ISNUMBER(SEARCH("Todos",'Menú y Pantallas'!$F11))),"X","") -> X | F11: =IF(OR(ISNUMBER(SEARCH(F$1,'Menú y Pantallas'!$F11)),ISNUMBER(SEARCH("Todos",'Menú y Pantallas'!$F11))),"X","") | G11: =IF(OR(ISNUMBER(SEARCH(G$1,'Menú y Pantallas'!$F11)),ISNUMBER(SEARCH("Todos",'Menú y Pantallas'!$F11))),"X","") | H11: =IF(OR(ISNUMBER(SEARCH(H$1,'Menú y Pantallas'!$F11)),ISNUMBER(SEARCH("Todos",'Menú y Pantallas'!$F11))),"X","") | I11: =IF(OR(ISNUMBER(SEARCH(I$1,'Menú y Pantallas'!$F11)),ISNUMBER(SEARCH("Todos",'Menú y Pantallas'!$F11))),"X","") | J11: =IF(OR(ISNUMBER(SEARCH(J$1,'Menú y Pantallas'!$F11)),ISNUMBER(SEARCH("Todos",'Menú y Pantallas'!$F11))),"X","") | ... L11: =IF(OR(ISNUMBER(SEARCH(L$1,'Menú y Pantallas'!$F11)),ISNUMBER(SEARCH("Todos",'Menú y Pantallas'!$F11))),"X","")
A12: ='Menú y Pantallas'!C12 -> 3.3 | B12: ='Menú y Pantallas'!D12 -> Inspección de calidad | C12: =IF(OR(ISNUMBER(SEARCH(C$1,'Menú y Pantallas'!$F12)),ISNUMBER(SEARCH("Todos",'Menú y Pantallas'!$F12))),"X","") | D12: =IF(OR(ISNUMBER(SEARCH(D$1,'Menú y Pantallas'!$F12)),ISNUMBER(SEARCH("Todos",'Menú y Pantallas'!$F12))),"X","") -> X | E12: =IF(OR(ISNUMBER(SEARCH(E$1,'Menú y Pantallas'!$F12)),ISNUMBER(SEARCH("Todos",'Menú y Pantallas'!$F12))),"X","") | F12: =IF(OR(ISNUMBER(SEARCH(F$1,'Menú y Pantallas'!$F12)),ISNUMBER(SEARCH("Todos",'Menú y Pantallas'!$F12))),"X","") | G12: =IF(OR(ISNUMBER(SEARCH(G$1,'Menú y Pantallas'!$F12)),ISNUMBER(SEARCH("Todos",'Menú y Pantallas'!$F12))),"X","") | H12: =IF(OR(ISNUMBER(SEARCH(H$1,'Menú y Pantallas'!$F12)),ISNUMBER(SEARCH("Todos",'Menú y Pantallas'!$F12))),"X","") -> X | I12: =IF(OR(ISNUMBER(SEARCH(I$1,'Menú y Pantallas'!$F12)),ISNUMBER(SEARCH("Todos",'Menú y Pantallas'!$F12))),"X","") | J12: =IF(OR(ISNUMBER(SEARCH(J$1,'Menú y Pantallas'!$F12)),ISNUMBER(SEARCH("Todos",'Menú y Pantallas'!$F12))),"X","") | ... L12: =IF(OR(ISNUMBER(SEARCH(L$1,'Menú y Pantallas'!$F12)),ISNUMBER(SEARCH("Todos",'Menú y Pantallas'!$F12))),"X","")
A13: ='Menú y Pantallas'!C13 -> 3.4 | B13: ='Menú y Pantallas'!D13 -> Putaway | C13: =IF(OR(ISNUMBER(SEARCH(C$1,'Menú y Pantallas'!$F13)),ISNUMBER(SEARCH("Todos",'Menú y Pantallas'!$F13))),"X","") | D13: =IF(OR(ISNUMBER(SEARCH(D$1,'Menú y Pantallas'!$F13)),ISNUMBER(SEARCH("Todos",'Menú y Pantallas'!$F13))),"X","") | E13: =IF(OR(ISNUMBER(SEARCH(E$1,'Menú y Pantallas'!$F13)),ISNUMBER(SEARCH("Todos",'Menú y Pantallas'!$F13))),"X","") -> X | F13: =IF(OR(ISNUMBER(SEARCH(F$1,'Menú y Pantallas'!$F13)),ISNUMBER(SEARCH("Todos",'Menú y Pantallas'!$F13))),"X","") | G13: =IF(OR(ISNUMBER(SEARCH(G$1,'Menú y Pantallas'!$F13)),ISNUMBER(SEARCH("Todos",'Menú y Pantallas'!$F13))),"X","") | H13: =IF(OR(ISNUMBER(SEARCH(H$1,'Menú y Pantallas'!$F13)),ISNUMBER(SEARCH("Todos",'Menú y Pantallas'!$F13))),"X","") | I13: =IF(OR(ISNUMBER(SEARCH(I$1,'Menú y Pantallas'!$F13)),ISNUMBER(SEARCH("Todos",'Menú y Pantallas'!$F13))),"X","") | J13: =IF(OR(ISNUMBER(SEARCH(J$1,'Menú y Pantallas'!$F13)),ISNUMBER(SEARCH("Todos",'Menú y Pantallas'!$F13))),"X","") | ... L13: =IF(OR(ISNUMBER(SEARCH(L$1,'Menú y Pantallas'!$F13)),ISNUMBER(SEARCH("Todos",'Menú y Pantallas'!$F13))),"X","")
... A68: ='Menú y Pantallas'!C68 -> 11.10 | B68: ='Menú y Pantallas'!D68 -> Documentos fiscales | C68: =IF(OR(ISNUMBER(SEARCH(C$1,'Menú y Pantallas'!$F68)),ISNUMBER(SEARCH("Todos",'Menú y Pantallas'!$F68))),"X","") -> X | D68: =IF(OR(ISNUMBER(SEARCH(D$1,'Menú y Pantallas'!$F68)),ISNUMBER(SEARCH("Todos",'Menú y Pantallas'!$F68))),"X","") | E68: =IF(OR(ISNUMBER(SEARCH(E$1,'Menú y Pantallas'!$F68)),ISNUMBER(SEARCH("Todos",'Menú y Pantallas'!$F68))),"X","") | F68: =IF(OR(ISNUMBER(SEARCH(F$1,'Menú y Pantallas'!$F68)),ISNUMBER(SEARCH("Todos",'Menú y Pantallas'!$F68))),"X","") | G68: =IF(OR(ISNUMBER(SEARCH(G$1,'Menú y Pantallas'!$F68)),ISNUMBER(SEARCH("Todos",'Menú y Pantallas'!$F68))),"X","") | H68: =IF(OR(ISNUMBER(SEARCH(H$1,'Menú y Pantallas'!$F68)),ISNUMBER(SEARCH("Todos",'Menú y Pantallas'!$F68))),"X","") | I68: =IF(OR(ISNUMBER(SEARCH(I$1,'Menú y Pantallas'!$F68)),ISNUMBER(SEARCH("Todos",'Menú y Pantallas'!$F68))),"X","") | J68: =IF(OR(ISNUMBER(SEARCH(J$1,'Menú y Pantallas'!$F68)),ISNUMBER(SEARCH("Todos",'Menú y Pantallas'!$F68))),"X","") | ... L68: =IF(OR(ISNUMBER(SEARCH(L$1,'Menú y Pantallas'!$F68)),ISNUMBER(SEARCH("Todos",'Menú y Pantallas'!$F68))),"X","") -> X
B70: Pantallas por rol | C70: =COUNTIF(C2:C68,"X") -> 30 | D70: =COUNTIF(D2:D68,"X") -> 42 | E70: =COUNTIF(E2:E68,"X") -> 9 | F70: =COUNTIF(F2:F68,"X") -> 6 | G70: =COUNTIF(G2:G68,"X") -> 4 | H70: =COUNTIF(H2:H68,"X") -> 5 | I70: =COUNTIF(I2:I68,"X") -> 11 | J70: =COUNTIF(J2:J68,"X") -> 12 | ... L70: =COUNTIF(L2:L68,"X") -> 17
B72: Se genera automáticamente desde la columna Roles de la hoja 'Menú y Pantallas'. Para 4.1 ('Todos según permisos') se marcan todos los roles.

Sheet Roles
A1: Código | B1: Rol | C1: Descripción | D1: Pantallas asignadas
A2: ADM | B2: Administrador | C2: Configura el sistema, usuarios, integraciones y parámetros globales | D2: ='Matriz Roles'!C70 -> 30
A3: JB | B3: Jefe de Bodega | C3: Supervisa la operación de la bodega y aprueba traspasos, ajustes y bajas | D3: ='Matriz Roles'!D70 -> 42
A4: REC | B4: Operario de recepción | C4: Recibe mercancía, ejecuta putaway y conteos | D4: ='Matriz Roles'!E70 -> 9
A5: PCK | B5: Operario de picking | C5: Recolecta pedidos en terminal móvil | D5: ='Matriz Roles'!F70 -> 6
A6: PKG | B6: Operario de packing | C6: Empaca, pesa, etiqueta y entrega en muelle | D6: ='Matriz Roles'!G70 -> 4
A7: CAL | B7: Inspector de calidad | C7: Inspecciona, bloquea y libera mercancía | D7: ='Matriz Roles'!H70 -> 5
A8: AUD | B8: Auditor | C8: Controla conteos, ajustes, bajas y trazabilidad | D8: ='Matriz Roles'!I70 -> 11
A9: COM | B9: Comprador | C9: Gestiona necesidad de compra, OC y proveedores | D9: ='Matriz Roles'!J70 -> 12
A10: TRA | B10: Coordinador de transporte | C10: Gestiona transportistas, guías, tracking y excepciones de entrega (rol nuevo) | D10: ='Matriz Roles'!K70 -> 12
A11: GER | B11: Gerencia | C11: Solo lectura, con aprobaciones de montos mayores | D11: ='Matriz Roles'!L70 -> 17

Sheet Resumen Módulos
A1: Módulo N° | B1: Módulo | C1: Nº de pantallas
A2: 1 | B2: Dashboard e Indicadores | C2: =COUNTIF('Menú y Pantallas'!$A$2:$A$68,A2) -> 3
A3: 2 | B3: Multi-Bodega y Ubicaciones | C3: =COUNTIF('Menú y Pantallas'!$A$2:$A$68,A3) -> 5
A4: 3 | B4: Recepción e Ingresos | C4: =COUNTIF('Menú y Pantallas'!$A$2:$A$68,A4) -> 6
A5: 4 | B5: Existencias y Stock | C5: =COUNTIF('Menú y Pantallas'!$A$2:$A$68,A5) -> 7
A6: 5 | B6: Ventas y Pedidos (API) | C6: =COUNTIF('Menú y Pantallas'!$A$2:$A$68,A6) -> 7
A7: 6 | B7: Compras y Reabastecimiento | C7: =COUNTIF('Menú y Pantallas'!$A$2:$A$68,A7) -> 5
A8: 7 | B8: Preparación y Despachos | C8: =COUNTIF('Menú y Pantallas'!$A$2:$A$68,A8) -> 6
A9: 8 | B9: Transporte y Última Milla | C9: =COUNTIF('Menú y Pantallas'!$A$2:$A$68,A9) -> 7
A10: 9 | B10: Devoluciones de Clientes | C10: =COUNTIF('Menú y Pantallas'!$A$2:$A$68,A10) -> 4
A11: 10 | B11: Mermas, Rezagados y Calidad | C11: =COUNTIF('Menú y Pantallas'!$A$2:$A$68,A11) -> 7
A12: 11 | B12: Configuración General | C12: =COUNTIF('Menú y Pantallas'!$A$2:$A$68,A12) -> 10
B13: Total | C13: =SUM(C2:C12) -> 67
